filterify/__init__.py
filterify/base.py
filterify/dependency.py
filterify/exceptions.py
filterify/main.py
filterify/parser.py
filterify/py.typed
filterify/validation.py
filterify/filters/__init__.py
filterify/filters/base.py
filterify-0.0.1.dist-info/LICENSE
filterify-0.0.1.dist-info/WHEEL
filterify-0.0.1.dist-info/METADATA
filterify-0.0.1.dist-info/RECORD
